chainlit/copilot/dist/assets/logo_dark-2a3cf740.svg
chainlit/copilot/dist/assets/logo_light-b078e7bc.svg
chainlit/copilot/dist/index.js
chainlit/frontend/dist/assets/DailyMotion-3646fe83.js
chainlit/frontend/dist/assets/Facebook-680464c3.js
chainlit/frontend/dist/assets/FilePlayer-59c68b66.js
chainlit/frontend/dist/assets/Kaltura-a3eb707c.js
chainlit/frontend/dist/assets/Mixcloud-882a543d.js
chainlit/frontend/dist/assets/Mux-9b949e85.js
chainlit/frontend/dist/assets/Preview-d01507e9.js
chainlit/frontend/dist/assets/SoundCloud-a2d55b9a.js
chainlit/frontend/dist/assets/Streamable-4234d739.js
chainlit/frontend/dist/assets/Twitch-84cdf717.js
chainlit/frontend/dist/assets/Vidyard-739d84e0.js
chainlit/frontend/dist/assets/Vimeo-1b11b4cf.js
chainlit/frontend/dist/assets/Wistia-11f72acf.js
chainlit/frontend/dist/assets/YouTube-7a96767f.js
chainlit/frontend/dist/assets/index-d088547c.css
chainlit/frontend/dist/assets/index-ee09a41e.js
chainlit/frontend/dist/assets/logo_dark-2a3cf740.svg
chainlit/frontend/dist/assets/logo_light-b078e7bc.svg
chainlit/frontend/dist/assets/react-plotly-d2500c3f.js
chainlit/frontend/dist/favicon.svg
chainlit/frontend/dist/index.html
chainlo/__init__.py
chainlo/__main__.py
chainlo/action.py
chainlo/auth.py
chainlo/cache.py
chainlo/chainlit.md
chainlo/chat_settings.py
chainlo/cli/__init__.py
chainlo/cli/utils.py
chainlo/config.py
chainlo/context.py
chainlo/copilot/dist/assets/logo_dark-2a3cf740.svg
chainlo/copilot/dist/assets/logo_light-b078e7bc.svg
chainlo/copilot/dist/index.js
chainlo/data/__init__.py
chainlo/data/acl.py
chainlo/data/sql_alchemy.py
chainlo/data/storage_clients.py
chainlo/discord/__init__.py
chainlo/discord/app.py
chainlo/element.py
chainlo/emitter.py
chainlo/frontend/dist/assets/DailyMotion-70cfb37f.js
chainlo/frontend/dist/assets/Facebook-65a6e347.js
chainlo/frontend/dist/assets/FilePlayer-4ef8abef.js
chainlo/frontend/dist/assets/Kaltura-a5020731.js
chainlo/frontend/dist/assets/Mixcloud-40151df3.js
chainlo-1.1.702.dist-info/METADATA
chainlo-1.1.702.dist-info/WHEEL
chainlo-1.1.702.dist-info/entry_points.txt
chainlo-1.1.702.dist-info/RECORD
